README.md
setup.py
microutil/__init__.py
microutil/_json.py
microutil/compress.py
microutil/exceptions.py
microutil/md5.py
microutil/util.py
microutil/wrap.py
microutil.egg-info/PKG-INFO
microutil.egg-info/SOURCES.txt
microutil.egg-info/dependency_links.txt
microutil.egg-info/requires.txt
microutil.egg-info/top_level.txt
microutil/server/__init__.py
microutil/server/compress.py
microutil/server/discovery.py
microutil/server/method.py
microutil/server/proxy.py
microutil/server/serialize.py
microutil/server/site.py
microutil/server/zookeeper.py