Metadata-Version: 2.1
Name: microutil
Version: 1.0.6
Summary: 基于django框架集成zookeeper分布式微服务的服务注册与发现工具包，方便HTTP远程调用
Home-page: https://github.com/autohawkeye/microutil.git
Author: sunshine
Author-email: firstsoft@163.com
License: UNKNOWN
Platform: UNKNOWN
Classifier: Programming Language :: Python :: 3
Classifier: License :: OSI Approved :: MIT License
Classifier: Operating System :: OS Independent
Requires-Python: >=3
